rhizo/__init__.py
rhizo/__init__.pyi
rhizo/__main__.py
rhizo/cache.py
rhizo/cli.py
rhizo/database.py
rhizo/engine.py
rhizo/exceptions.py
rhizo/logging.py
rhizo/olap_engine.py
rhizo/py.typed
rhizo/reader.py
rhizo/subscriber.py
rhizo/transaction.py
rhizo/writer.py
rhizo-0.5.3.dist-info/METADATA
rhizo-0.5.3.dist-info/WHEEL
rhizo-0.5.3.dist-info/entry_points.txt
rhizo-0.5.3.dist-info/top_level.txt
rhizo-0.5.3.dist-info/RECORD
