Metadata-Version: 2.4
Name: rhizo
Version: 0.5.3
Summary: Data, connected. Versioned data with SQL, time travel, and cross-table ACID transactions.
License: MIT
Project-URL: Homepage, https://rhizodata.dev
Project-URL: Repository, https://github.com/rhizodata/rhizo
Keywords: data,sql,duckdb,arrow,versioning,time-travel,transactions
Classifier: Development Status :: 3 - Alpha
Classifier: Intended Audience :: Developers
Classifier: License :: OSI Approved :: MIT License
Classifier: Programming Language :: Python :: 3
Classifier: Programming Language :: Python :: 3.9
Classifier: Programming Language :: Python :: 3.10
Classifier: Programming Language :: Python :: 3.11
Classifier: Programming Language :: Python :: 3.12
Classifier: Topic :: Database
Classifier: Topic :: Software Development :: Libraries
Requires-Python: >=3.9
Requires-Dist: rhizo-core>=0.5.3
Requires-Dist: pyarrow>=14.0.0
Requires-Dist: duckdb>=0.9.0
Requires-Dist: pandas>=2.0.0
Provides-Extra: fast
Requires-Dist: datafusion>=35.0.0; extra == "fast"
Provides-Extra: dev
Requires-Dist: pytest>=7.0.0; extra == "dev"
Requires-Dist: maturin>=1.0.0; extra == "dev"
Requires-Dist: ruff>=0.1.0; extra == "dev"
Requires-Dist: datafusion>=35.0.0; extra == "dev"
